tiipbusclient/__init__.py
tiipbusclient/tiipclient.py
tiipbusclient-1.1.2.dist-info/LICENSE.txt
tiipbusclient-1.1.2.dist-info/METADATA
tiipbusclient-1.1.2.dist-info/RECORD
tiipbusclient-1.1.2.dist-info/WHEEL
tiipbusclient-1.1.2.dist-info/top_level.txt
